pyudevmonitor
