Metadata-Version: 1.1
Name: pyudevmonitor
Version: 0.1.1
Summary: simple wrapper of udevadm monitor
Home-page: https://github.com/williamfzc/pyudevmonitor
Author: williamfzc
Author-email: fengzc@vip.qq.com
License: MIT
Platform: UNKNOWN
Classifier: License :: OSI Approved :: MIT License
Classifier: Programming Language :: Python
Classifier: Programming Language :: Python :: 3
